{
  "case": [
    "Encompassed",
    "ScopeOfClaim",
    "Embodied",
    "Hindsight",
    "WrittenFormulation",
    "BasicFormulation"
  ],
  "evaluated_nodes": [
    "Encompassed",
    "ScopeOfClaim",
    "Embodied",
    "Hindsight",
    "WrittenFormulation",
    "BasicFormulation"
  ],
  "reasoning": [
    {
      "depth": 0,
      "statement": "no reason to believe the skilled person would have arrived at the proposed invention"
    },
    {
      "depth": 1,
      "statement": "There is no valid objective technical problem formulation"
    },
    {
      "depth": 2,
      "statement": "There are no non-technical contributions constraining the objective technical problem"
    },
    {
      "depth": 3,
      "statement": "The written formulation has been formed with hindsight"
    },
    {
      "depth": 4,
      "statement": "We have a valid basic formulation of the objective technical problem"
    }
  ]
}